setup.py
GB22distributions/Binomialdistribution.py
GB22distributions/Gaussiandistribution.py
GB22distributions/Generaldistribution.py
GB22distributions/__init__.py
GB22distributions.egg-info/PKG-INFO
GB22distributions.egg-info/SOURCES.txt
GB22distributions.egg-info/dependency_links.txt
GB22distributions.egg-info/not-zip-safe
GB22distributions.egg-info/top_level.txt