Metadata-Version: 1.0
Name: GB22distributions
Version: 1.1
Summary: Gaussian and Binomial distributions
Home-page: UNKNOWN
Author: bayode
Author-email: UNKNOWN
License: UNKNOWN
Platform: UNKNOWN
